django_leaflet_gpx/__init__.py
django_leaflet_gpx/apps.py
django_leaflet_gpx/migrations/__init__.py
django_leaflet_gpx/models.py
django_leaflet_gpx/settings.py
django_leaflet_gpx/static/leaflet-gpx/css/images/layers-2x.png
django_leaflet_gpx/static/leaflet-gpx/css/images/layers.png
django_leaflet_gpx/static/leaflet-gpx/css/images/marker-icon-2x.png
django_leaflet_gpx/static/leaflet-gpx/css/images/marker-icon.png
django_leaflet_gpx/static/leaflet-gpx/css/images/marker-shadow.png
django_leaflet_gpx/static/leaflet-gpx/css/leaflet-1.5.1.css
django_leaflet_gpx/static/leaflet-gpx/icons/finish.png
django_leaflet_gpx/static/leaflet-gpx/icons/marker.png
django_leaflet_gpx/static/leaflet-gpx/icons/start.png
django_leaflet_gpx/static/leaflet-gpx/js/leaflet-1.5.1.js
django_leaflet_gpx/static/leaflet-gpx/js/leaflet-1.5.1.js.map
django_leaflet_gpx/static/leaflet-gpx/js/leaflet-gpx-1.4.0.js
django_leaflet_gpx/static/leaflet-gpx/js/leaflet-gpx-map.js
django_leaflet_gpx/templates/leaflet-gpx/css.html
django_leaflet_gpx/templates/leaflet-gpx/js.html
django_leaflet_gpx/templates/leaflet-gpx/map-gpx.html
django_leaflet_gpx/templates/leaflet-gpx/map-simple.html
django_leaflet_gpx/templatetags/__init__.py
django_leaflet_gpx/templatetags/leaflet_gpx.py
django_leaflet_gpx/tests.py
django_leaflet_gpx-0.1.3.dist-info/LICENSE
django_leaflet_gpx-0.1.3.dist-info/WHEEL
django_leaflet_gpx-0.1.3.dist-info/METADATA
django_leaflet_gpx-0.1.3.dist-info/RECORD
